README.md
setup.py
C:/Users/Administrator/PycharmProjects/pyunit-prime/pyunit_prime/prime.c
pyunit_prime/__init__.py
pyunit_prime/cli.py
pyunit_prime/prime.c
pyunit_prime/prime.py
pyunit_prime.egg-info/PKG-INFO
pyunit_prime.egg-info/SOURCES.txt
pyunit_prime.egg-info/dependency_links.txt
pyunit_prime.egg-info/entry_points.txt
pyunit_prime.egg-info/not-zip-safe
pyunit_prime.egg-info/top_level.txt