Metadata-Version: 2.1
Name: pyunit-prime
Version: 2020.3.21
Summary: 质数处理和寻找质数的模块
Home-page: https://github.com/PyUnit/pyunit-prime
Author: Jtyoui
Author-email: jtyoui@qq.com
License: MIT Licence
Platform: any
Classifier: Programming Language :: Python :: 3
Classifier: Programming Language :: C
Classifier: License :: OSI Approved :: MIT License
Classifier: Operating System :: Microsoft :: Windows
Classifier: Operating System :: POSIX :: Linux
